asyncns/__init__.py
asyncns/api_client.py
asyncns-0.0.6.dist-info/LICENSE
asyncns-0.0.6.dist-info/METADATA
asyncns-0.0.6.dist-info/WHEEL
asyncns-0.0.6.dist-info/top_level.txt
asyncns-0.0.6.dist-info/RECORD
