Metadata-Version: 2.1
Name: asyncns
Version: 0.0.6
Summary: An async API wrapper for NationStates
Home-page: https://github.com/AavHRF/asyncns
Author: Aav
Author-email: aav.verinhall@gmail.com
License: UNKNOWN
Project-URL: Bug Tracker, https://github.com/AavHRF/asyncns/issues
Platform: UNKNOWN
Classifier: Programming Language :: Python :: 3
Classifier: License :: OSI Approved :: MIT License
Classifier: Operating System :: OS Independent
Requires-Python: >=3.6
License-File: LICENSE
